excelcleaner/__init__.py
excelcleaner/_excelCleaner.py
excelcleaner-0.0.18.dist-info/METADATA
excelcleaner-0.0.18.dist-info/WHEEL
excelcleaner-0.0.18.dist-info/licenses/LICENSE.txt
excelcleaner-0.0.18.dist-info/RECORD
