Metadata-Version: 2.1
Name: excelcleaner
Version: 0.0.18
Summary: A packages that helps you clean and recover columns of Excel data converted from PDF files.
Project-URL: Homepage, https://github.com/generateNscore/excelcleaner
Author-email: Sukmock Lee <smlee@inha.ac.kr>
License-File: LICENSE.txt
Classifier: Development Status :: 5 - Production/Stable
Classifier: Intended Audience :: End Users/Desktop
Classifier: Intended Audience :: Financial and Insurance Industry
Classifier: License :: OSI Approved :: MIT License
Classifier: Operating System :: OS Independent
Classifier: Programming Language :: Python :: 3
Classifier: Topic :: Office/Business :: Financial :: Accounting
Classifier: Topic :: Office/Business :: Financial :: Point-Of-Sale
Classifier: Topic :: Office/Business :: Financial :: Spreadsheet
Requires-Python: >=3.7
